grains/__init__.py
grains/grains.py
grainsy-1.0.2.dist-info/METADATA
grainsy-1.0.2.dist-info/WHEEL
grainsy-1.0.2.dist-info/top_level.txt
grainsy-1.0.2.dist-info/RECORD
