Metadata-Version: 2.1
Name: grainsy
Version: 1.0.2
Summary: Library for calculating grains on a chessboard
Author: Vajo Sekulic
Author-email: hello@bekindstudio.at
Requires-Python: >=3.11
